CHANGELOG.rst
LICENSE
MANIFEST.in
README.rst
setup.cfg
setup.py
docs/make.bat
docs/source/api.rst
docs/source/changelog.rst
docs/source/conf.py
docs/source/contributing.rst
docs/source/example.rst
docs/source/faq.rst
docs/source/index.rst
docs/source/introduction.rst
examples/get_areas.py
examples/get_nodes.py
examples/get_ways.py
overpy/__about__.py
overpy/__init__.py
overpy/exception.py
overpy/helper.py
overpy.egg-info/PKG-INFO
overpy.egg-info/SOURCES.txt
overpy.egg-info/dependency_links.txt
overpy.egg-info/not-zip-safe
overpy.egg-info/top_level.txt
tests/__init__.py
tests/base_class.py
tests/test_exception.py
tests/test_json.py
tests/test_request.py
tests/test_result.py
tests/test_result_way.py
tests/test_xml.py
tests/json/area-01.json
tests/json/node-01.json
tests/json/relation-01.json
tests/json/relation-02.json
tests/json/relation-03.json
tests/json/relation-04.json
tests/json/remark-runtime-error-01.json
tests/json/remark-runtime-remark-01.json
tests/json/remark-unknown-01.json
tests/json/result-expand-01.json
tests/json/result-expand-02.json
tests/json/result-way-01.json
tests/json/result-way-02.json
tests/json/result-way-03.json
tests/json/way-01.json
tests/json/way-02.json
tests/json/way-03.json
tests/json/way-04.json
tests/response/bad-request-encoding.html
tests/response/bad-request.html
tests/xml/area-01.xml
tests/xml/node-01.xml
tests/xml/relation-01.xml
tests/xml/relation-02.xml
tests/xml/relation-03.xml
tests/xml/relation-04.xml
tests/xml/remark-runtime-error-01.xml
tests/xml/remark-runtime-remark-01.xml
tests/xml/remark-unknown-01.xml
tests/xml/way-01.xml
tests/xml/way-02.xml
tests/xml/way-03.xml
tests/xml/way-04.xml