Metadata-Version: 1.1
Name: overpy
Version: 0.5
Summary: Python Wrapper to access the OpenStreepMap Overpass API
Home-page: https://github.com/DinoTools/python-overpy
Author: PhiBo (DinoTools)
Author-email: UNKNOWN
License: MIT
Keywords: OverPy Overpass OSM OpenStreetMap
Platform: UNKNOWN
Classifier: Development Status :: 4 - Beta
Classifier: License :: OSI Approved :: MIT License
Classifier: Operating System :: OS Independent
Classifier: Programming Language :: Python
Classifier: Programming Language :: Python :: 2.7
Classifier: Programming Language :: Python :: 3
Classifier: Programming Language :: Python :: 3.2
Classifier: Programming Language :: Python :: 3.3
Classifier: Programming Language :: Python :: 3.4
Classifier: Programming Language :: Python :: 3.5
Classifier: Programming Language :: Python :: 3.6
Classifier: Programming Language :: Python :: Implementation :: CPython
Classifier: Programming Language :: Python :: Implementation :: PyPy
